htmlfilesforquiz/__init__.py
htmlfilesforquiz/_common.py
htmlfilesforquiz/_generateEm.py
htmlfilesforquiz/_generateMakeHTMLs.py
htmlfilesforquiz/_scoreEm.py
htmlfilesforquiz/makeChoices.py
htmlfilesforquiz-0.0.16.dist-info/METADATA
htmlfilesforquiz-0.0.16.dist-info/WHEEL
htmlfilesforquiz-0.0.16.dist-info/licenses/LICENSE.txt
htmlfilesforquiz-0.0.16.dist-info/RECORD
