Metadata-Version: 2.1
Name: htmlfilesforquiz
Version: 0.0.16
Summary: A package that generates question papers as HTML files to be distributed over the network and grades the answers in text files submitted by students.
Project-URL: Homepage, https://github.com/generateNscore/htmlfilesforquiz
Project-URL: Bug Tracker, https://github.com/generateNscore/htmlfilesforquiz/issues
Author-email: Sukmock Lee <smlee@inha.ac.kr>
License-File: LICENSE.txt
Classifier: Development Status :: 4 - Beta
Classifier: Intended Audience :: Education
Classifier: Intended Audience :: End Users/Desktop
Classifier: License :: OSI Approved :: MIT License
Classifier: Operating System :: OS Independent
Classifier: Programming Language :: Python :: 3
Classifier: Topic :: Education :: Testing
Requires-Python: >=3.7
